{
    "Estados":[
         {
            "Es": "Aguascalientes"
         },
         {
            "Es": "Baja California"
         },
         {
            "Es": "Baja California Sur"
         },
         {
            "Es": "Campeche"
         },
         {
            "Es": "Coahuila"
         },
         {
            "Es": "Colima"
         },
         {
            "Es": "Chihuahua"
         },
         {
            "Es": "Ciudad de Mexico"
         },
         {
            "Es": "Durango"
         },
         {
            "Es": "Guanajuato"
         },
         {
            "Es": "Hidalgo"
         },
         {
            "Es": "Estado de Mexico"
         },
         {
            "Es": "Michoacan"
         },
         {
            "Es": "Morelos"
         },
         {
            "Es": "Nayarit"
         },
         {
            "Es": "Nuevo Leon"
         },


         {
            "Es": "Oaxaca"
         },
         {
            "Es": "Puebla"
         },
         {
            "Es": "Queretaro"
         },
         {
            "Es": "Quintana Roo"
         },
         {
            "Es": "San Luis Potosi"
         },
         {
            "Es": "Sinaloa"
         },
         {
            "Es": "Sonora"
         },
         {
            "Es": "Tabasco"
         },
         {
            "Es": "Tamaulipas"
         },
         {
            "Es": "Tlaxcala"
         },
         {
            "Es": "Veracruz"
         },
         {
            "Es": "Yucatan"
         },
         {
            "Es": "Zacatecas"
         }

     ]
    
 }
